neuron_reduce/__init__.py
neuron_reduce/reducing_methods.py
neuron_reduce/subtree_reductor_func.py
neuron_reduce-0.0.7.dist-info/LICENSE
neuron_reduce-0.0.7.dist-info/METADATA
neuron_reduce-0.0.7.dist-info/WHEEL
neuron_reduce-0.0.7.dist-info/top_level.txt
neuron_reduce-0.0.7.dist-info/RECORD
