Metadata-Version: 2.1
Name: neuron-reduce
Version: 0.0.7
Summary: Efficient analytical reduction of nonlinear detailed neuron models
Home-page: https://github.com/orena1/neuron_reduce
Author: Oren Amsalem, Guy Eyal, Noa Rogozinski, Michael Gevaert, Idan Segev
Author-email: oren.amsalem1@mail.huji.ac.il
License: UNKNOWN
Platform: UNKNOWN
Classifier: Programming Language :: Python :: 2
Classifier: Programming Language :: Python :: 3
Classifier: License :: OSI Approved :: MIT License
Classifier: Operating System :: OS Independent
